<?xml version="1.0" encoding="UTF-8" standalone="no"?>
<!DOCTYPE tiles-definitions PUBLIC "-//Apache Software Foundation//DTD Tiles Configuration 3.0//EN" "http://tiles.apache.org/dtds/tiles-config_3_0.dtd">
<tiles-definitions>
    <definition extends="default" name="instanceorgs/list">
        <put-attribute name="body" value="/WEB-INF/views/instanceorgs/list.jspx"/>
    </definition>
<definition extends="default" name="instanceorgs/show">
        <put-attribute name="body" value="/WEB-INF/views/instanceorgs/show.jspx"/>
    </definition>
<definition extends="default" name="instanceorgs/create">
        <put-attribute name="body" value="/WEB-INF/views/instanceorgs/create.jspx"/>
    </definition>
<definition extends="default" name="instanceorgs/update">
        <put-attribute name="body" value="/WEB-INF/views/instanceorgs/update.jspx"/>
    </definition>
</tiles-definitions>
